pysolidtime/__init__.py
pysolidtime/cli.py
pysolidtime/client.py
pysolidtime-0.1.1.dist-info/METADATA
pysolidtime-0.1.1.dist-info/WHEEL
pysolidtime-0.1.1.dist-info/entry_points.txt
pysolidtime-0.1.1.dist-info/RECORD
