Metadata-Version: 2.3
Name: pysolidtime
Version: 0.1.1
Summary: A Python client and CLI for SolidTime time tracking.
Author: Edmundo Sanchez
Author-email: eddi@heyeddi.com
Requires-Python: >=3.13
Classifier: Programming Language :: Python :: 3
Classifier: Programming Language :: Python :: 3.13
Requires-Dist: requests (>=2.32.3,<3.0.0)
Requires-Dist: typer (>=0.15.2,<0.16.0)
Project-URL: Documentation, https://gitlab.com/bass03/pySolidTime/blob/main/README.md
Project-URL: Homepage, https://gitlab.com/bass03/pySolidTime
Project-URL: Repository, https://gitlab.com/bass03/pySolidTime
